cap6635/README.md
cap6635/__init__.py
cap6635/agents/README.md
cap6635/agents/__init__.py
cap6635/agents/adversarialsearch/minimax.py
cap6635/agents/blindsearch/__init__.py
cap6635/agents/blindsearch/vacuum.py
cap6635/agents/localsearch/__init__.py
cap6635/agents/localsearch/genetic.py
cap6635/agents/localsearch/hill_climbing.py
cap6635/agents/localsearch/simulated_annealing.py
cap6635/environment/__init__.py
cap6635/environment/map.py
cap6635/environment/queens.py
cap6635/utilities/README.md
cap6635/utilities/__init__.py
cap6635/utilities/constants.py
cap6635/utilities/location.py
cap6635/utilities/node.py
cap6635/utilities/plot.py
cap6635/utilities/timer.py
cap6635-0.0.8.dist-info/METADATA
cap6635-0.0.8.dist-info/WHEEL
cap6635-0.0.8.dist-info/licenses/LICENSE
cap6635-0.0.8.dist-info/RECORD
