Metadata-Version: 2.1
Name: cap6635
Version: 0.0.8
Summary: A Summary of AI Techniques covered in cap 6635
Project-URL: Homepage, https://github.com/nickumia/cap6635
Project-URL: Bug Tracker, https://github.com/nickumia/cap6635/issues
Author-email: nickumia <nickumia6@gmail.com>
License-File: LICENSE
Classifier: License :: OSI Approved :: MIT License
Classifier: Operating System :: OS Independent
Classifier: Programming Language :: Python :: 3
Requires-Python: >=3.7
Requires-Dist: imageio
Requires-Dist: matplotlib
Requires-Dist: numpy
